LICENSE
MANIFEST.in
README.md
setup.py
appenlight_diamond/__init__.py
appenlight_diamond.egg-info/PKG-INFO
appenlight_diamond.egg-info/SOURCES.txt
appenlight_diamond.egg-info/dependency_links.txt
appenlight_diamond.egg-info/entry_points.txt
appenlight_diamond.egg-info/top_level.txt
appenlight_diamond.egg-info/zip-safe