Metadata-Version: 1.1
Name: appenlight-diamond
Version: 0.1.0
Summary: Python-Diamond handler for App Enlight (http://appenlight.com)
Home-page: UNKNOWN
Author: Marcin Lulek
Author-email: info@webreactor.eu
License: BSD
Platform: UNKNOWN
Classifier: Intended Audience :: Developers
Classifier: License :: DFSG approved
Classifier: License :: OSI Approved :: BSD License
Classifier: Operating System :: OS Independent
Classifier: Programming Language :: Python :: 2
Classifier: Programming Language :: Python :: 2.6
Classifier: Programming Language :: Python :: 2.7
Classifier: Programming Language :: Python :: 3.3
Classifier: Topic :: Software Development :: Libraries :: Python Modules
